SpringCloudJiaochengZhaiyongchao/README.md
SpringCloudJiaochengZhaiyongchao/__init__.py
SpringCloudJiaochengZhaiyongchao/__main__.py
SpringCloudJiaochengZhaiyongchao/file.epub
SpringCloudJiaochengZhaiyongchao/index.html
SpringCloudJiaochengZhaiyongchao/css/__init__.py
SpringCloudJiaochengZhaiyongchao/css/annotations.css
SpringCloudJiaochengZhaiyongchao/css/main.css
SpringCloudJiaochengZhaiyongchao/css/normalize.css
SpringCloudJiaochengZhaiyongchao/css/popup.css
SpringCloudJiaochengZhaiyongchao/font/__init__.py
SpringCloudJiaochengZhaiyongchao/font/fontello.eot
SpringCloudJiaochengZhaiyongchao/font/fontello.svg
SpringCloudJiaochengZhaiyongchao/font/fontello.ttf
SpringCloudJiaochengZhaiyongchao/font/fontello.woff
SpringCloudJiaochengZhaiyongchao/img/__init__.py
SpringCloudJiaochengZhaiyongchao/img/annotator-glyph-sprite.png
SpringCloudJiaochengZhaiyongchao/img/annotator-icon-sprite.png
SpringCloudJiaochengZhaiyongchao/img/apple-touch-icon.png
SpringCloudJiaochengZhaiyongchao/img/cancelfullscreen.png
SpringCloudJiaochengZhaiyongchao/img/close.png
SpringCloudJiaochengZhaiyongchao/img/fullscreen.png
SpringCloudJiaochengZhaiyongchao/img/loader.gif
SpringCloudJiaochengZhaiyongchao/img/menu-icon.png
SpringCloudJiaochengZhaiyongchao/img/save.png
SpringCloudJiaochengZhaiyongchao/img/saved.png
SpringCloudJiaochengZhaiyongchao/img/settings-s.png
SpringCloudJiaochengZhaiyongchao/img/settings.png
SpringCloudJiaochengZhaiyongchao/img/star.png
SpringCloudJiaochengZhaiyongchao/js/__init__.py
SpringCloudJiaochengZhaiyongchao/js/epub.js
SpringCloudJiaochengZhaiyongchao/js/epub.min.js
SpringCloudJiaochengZhaiyongchao/js/epub.min.map
SpringCloudJiaochengZhaiyongchao/js/hooks.min.js
SpringCloudJiaochengZhaiyongchao/js/hooks.min.map
SpringCloudJiaochengZhaiyongchao/js/reader.js
SpringCloudJiaochengZhaiyongchao/js/reader.js.map
SpringCloudJiaochengZhaiyongchao/js/reader.min.js
SpringCloudJiaochengZhaiyongchao/js/reader.min.map
SpringCloudJiaochengZhaiyongchao/js/hooks/__init__.py
spring_cloud_jiaocheng_zhaiyongchao-2024.3.2.0.dist-info/METADATA
spring_cloud_jiaocheng_zhaiyongchao-2024.3.2.0.dist-info/WHEEL
spring_cloud_jiaocheng_zhaiyongchao-2024.3.2.0.dist-info/entry_points.txt
spring_cloud_jiaocheng_zhaiyongchao-2024.3.2.0.dist-info/top_level.txt
spring_cloud_jiaocheng_zhaiyongchao-2024.3.2.0.dist-info/RECORD
